arl_dataclasses/__init__.py
arl_dataclasses/activity_stmts.py
arl_dataclasses/claims_refs.py
arl_dataclasses/decorators.py
arl_dataclasses/types.py
arl_dataclasses/impl/__init__.py
arl_dataclasses/impl/action_decl.py
arl_dataclasses/impl/action_decorator_impl.py
arl_dataclasses/impl/action_impl.py
arl_dataclasses/impl/activity_bind_impl.py
arl_dataclasses/impl/activity_block_meta_t.py
arl_dataclasses/impl/activity_decl.py
arl_dataclasses/impl/activity_decorator_impl.py
arl_dataclasses/impl/activity_parallel_impl.py
arl_dataclasses/impl/activity_parallel_meta_t.py
arl_dataclasses/impl/activity_replicate_impl.py
arl_dataclasses/impl/activity_scope_impl.py
arl_dataclasses/impl/activity_sequence_impl.py
arl_dataclasses/impl/activity_sequence_meta_t.py
arl_dataclasses/impl/activity_traverse_closure.py
arl_dataclasses/impl/backend.py
arl_dataclasses/impl/backend_asyncio.py
arl_dataclasses/impl/base_decorator_impl.py
arl_dataclasses/impl/base_t.py
arl_dataclasses/impl/bind_all_impl.py
arl_dataclasses/impl/component_decorator_impl.py
arl_dataclasses/impl/component_impl.py
arl_dataclasses/impl/constraint_impl.py
arl_dataclasses/impl/context.py
arl_dataclasses/impl/ctor.py
arl_dataclasses/impl/ctor_scope.py
arl_dataclasses/impl/decorator_impl_base.py
arl_dataclasses/impl/do_impl.py
arl_dataclasses/impl/do_impl_meta.py
arl_dataclasses/impl/exec_decorator_impl.py
arl_dataclasses/impl/exec_group.py
arl_dataclasses/impl/exec_kind_e.py
arl_dataclasses/impl/exec_type.py
arl_dataclasses/impl/extend_action_decorator_impl.py
arl_dataclasses/impl/extend_base_decorator_impl.py
arl_dataclasses/impl/extend_component_decorator_impl.py
arl_dataclasses/impl/extend_decorator_impl.py
arl_dataclasses/impl/extend_kind_e.py
arl_dataclasses/impl/field_claim_impl.py
arl_dataclasses/impl/field_pool_impl.py
arl_dataclasses/impl/flow_obj_kind_e.py
arl_dataclasses/impl/impl_base.py
arl_dataclasses/impl/input_meta_t.py
arl_dataclasses/impl/input_output_t.py
arl_dataclasses/impl/lock_meta_t.py
pyarl_dataclasses-0.0.1.3519958098.dist-info/LICENSE
pyarl_dataclasses-0.0.1.3519958098.dist-info/METADATA
pyarl_dataclasses-0.0.1.3519958098.dist-info/WHEEL
pyarl_dataclasses-0.0.1.3519958098.dist-info/top_level.txt
pyarl_dataclasses-0.0.1.3519958098.dist-info/RECORD
